setup.py
pyprophet_cli/__init__.py
pyprophet_cli/apply_weights.py
pyprophet_cli/common_options.py
pyprophet_cli/constants.py
pyprophet_cli/core.py
pyprophet_cli/exceptions.py
pyprophet_cli/io.py
pyprophet_cli/learn.py
pyprophet_cli/main.py
pyprophet_cli/prepare.py
pyprophet_cli/score.py
pyprophet_cli/subsample.py
pyprophet_cli/version.py
pyprophet_cli.egg-info/PKG-INFO
pyprophet_cli.egg-info/SOURCES.txt
pyprophet_cli.egg-info/dependency_links.txt
pyprophet_cli.egg-info/entry_points.txt
pyprophet_cli.egg-info/not-zip-safe
pyprophet_cli.egg-info/requires.txt
pyprophet_cli.egg-info/top_level.txt