Metadata-Version: 1.1
Name: pyprophet-cli
Version: 0.0.19
Summary: tools for running pyoprohet on a computing cluster
Home-page: UNKNOWN
Author: Uwe Schmitt
Author-email: uwe.schmitt@id.ethz.ch
License: BSD
Platform: UNKNOWN
Classifier: Development Status :: 3 - Alpha
Classifier: Environment :: Console
Classifier: Intended Audience :: Science/Research
Classifier: License :: OSI Approved :: BSD License
Classifier: Operating System :: OS Independent
Classifier: Topic :: Scientific/Engineering :: Bio-Informatics
Classifier: Topic :: Scientific/Engineering :: Chemistry
